{"log":[{"traceID":0,"events":[{"eventIndex":0,"eventType":"Access-Request","logLine":1,"timestamp":0},{"eventIndex":1,"eventType":"Access-Accept","logLine":2,"timestamp":64}]},{"traceID":1,"events":[{"eventIndex":0,"eventType":"Access-Request","logLine":3,"timestamp":0},{"eventIndex":1,"eventType":"Access-Accept","logLine":4,"timestamp":128}]},{"traceID":2,"events":[{"eventIndex":0,"eventType":"Access-Request","logLine":5,"timestamp":0},{"eventIndex":1,"eventType":"Access-Reject","logLine":6,"timestamp":64}]},{"traceID":3,"events":[{"eventIndex":0,"eventType":"Access-Request","logLine":7,"timestamp":0},{"eventIndex":1,"eventType":"Access-Reject","logLine":8,"timestamp":96}]},{"traceID":4,"events":[{"eventIndex":0,"eventType":"Access-Request","logLine":9,"timestamp":0},{"eventIndex":1,"eventType":"Access-Challenge","logLine":10,"timestamp":2048},{"eventIndex":2,"eventType":"Access-Request","logLine":11,"timestamp":2144},{"eventIndex":3,"eventType":"Access-Reject","logLine":12,"timestamp":2208}]},{"traceID":5,"events":[{"eventIndex":0,"eventType":"Access-Request","logLine":13,"timestamp":0},{"eventIndex":1,"eventType":"Access-Challenge","logLine":14,"timestamp":3072},{"eventIndex":2,"eventType":"Access-Request","logLine":15,"timestamp":3184},{"eventIndex":3,"eventType":"Access-Reject","logLine":16,"timestamp":3312}]},{"traceID":6,"events":[{"eventIndex":0,"eventType":"Access-Request","logLine":17,"timestamp":0},{"eventIndex":1,"eventType":"Access-Challenge","logLine":18,"timestamp":64},{"eventIndex":2,"eventType":"Access-Request","logLine":19,"timestamp":192},{"eventIndex":3,"eventType":"Access-Accept","logLine":20,"timestamp":320}]},{"traceID":7,"events":[{"eventIndex":0,"eventType":"Access-Request","logLine":21,"timestamp":0},{"eventIndex":1,"eventType":"Access-Challenge","logLine":22,"timestamp":128},{"eventIndex":2,"eventType":"Access-Request","logLine":23,"timestamp":256},{"eventIndex":3,"eventType":"Access-Accept","logLine":24,"timestamp":352}]}],"partitions":[{"eventType":"Access-Request","events":[{"traceID":4,"eventIndex":0},{"traceID":5,"eventIndex":0},{"traceID":7,"eventIndex":0},{"traceID":6,"eventIndex":0}]},{"eventType":"Access-Accept","events":[{"traceID":0,"eventIndex":1},{"traceID":1,"eventIndex":1},{"traceID":6,"eventIndex":3},{"traceID":7,"eventIndex":3}]},{"eventType":"Access-Reject","events":[{"traceID":2,"eventIndex":1},{"traceID":3,"eventIndex":1},{"traceID":4,"eventIndex":3},{"traceID":5,"eventIndex":3}]},{"eventType":"Access-Challenge","events":[{"traceID":4,"eventIndex":1},{"traceID":5,"eventIndex":1}]},{"eventType":"Access-Request","events":[{"traceID":0,"eventIndex":0},{"traceID":1,"eventIndex":0},{"traceID":2,"eventIndex":0},{"traceID":3,"eventIndex":0},{"traceID":4,"eventIndex":2},{"traceID":5,"eventIndex":2},{"traceID":6,"eventIndex":2},{"traceID":7,"eventIndex":2}]},{"eventType":"Access-Challenge","events":[{"traceID":7,"eventIndex":1},{"traceID":6,"eventIndex":1}]}],"invariants":[{"invariantType":"AlwaysPrecedes","predicates":["Access-Request","Access-Challenge"],"constraints":["lowerbound = 64"]},{"invariantType":"AlwaysPrecedes","predicates":["Access-Request","Access-Challenge"],"constraints":["upperbound = 3072"]},{"invariantType":"InterruptedBy","predicates":["Access-Request","Access-Challenge"],"constraints":["lowerbound = 192"]},{"invariantType":"InterruptedBy","predicates":["Access-Request","Access-Challenge"],"constraints":["upperbound = 3184"]},{"invariantType":"AlwaysPrecedes","predicates":["Access-Request","Access-Accept"],"constraints":["lowerbound = 64"]},{"invariantType":"AlwaysPrecedes","predicates":["Access-Request","Access-Accept"],"constraints":["upperbound = 352"]},{"invariantType":"AlwaysPrecedes","predicates":["Access-Request","Access-Reject"],"constraints":["lowerbound = 64"]},{"invariantType":"AlwaysPrecedes","predicates":["Access-Request","Access-Reject"],"constraints":["upperbound = 3312"]},{"invariantType":"AlwaysFollowedBy","predicates":["Access-Challenge","Access-Request"],"constraints":["lowerbound = 96"]},{"invariantType":"AlwaysFollowedBy","predicates":["Access-Challenge","Access-Request"],"constraints":["upperbound = 128"]},{"invariantType":"NeverFollowedBy","predicates":["Access-Challenge","Access-Challenge"]},{"invariantType":"NeverFollowedBy","predicates":["Access-Accept","Access-Request"]},{"invariantType":"NeverFollowedBy","predicates":["Access-Accept","Access-Challenge"]},{"invariantType":"NeverFollowedBy","predicates":["Access-Accept","Access-Accept"]},{"invariantType":"NeverFollowedBy","predicates":["Access-Accept","Access-Reject"]},{"invariantType":"NeverFollowedBy","predicates":["Access-Reject","Access-Request"]},{"invariantType":"NeverFollowedBy","predicates":["Access-Reject","Access-Challenge"]},{"invariantType":"NeverFollowedBy","predicates":["Access-Reject","Access-Accept"]},{"invariantType":"NeverFollowedBy","predicates":["Access-Reject","Access-Reject"]}]}